vmux/__init__.py
vmux/auth.py
vmux/cli.py
vmux/client.py
vmux/config.py
vmux/core.py
vmux/deps.py
vmux/packager.py
vmux/runner.py
vmux/terminal.py
vmux/types.py
vmux/ui.py
vmux/claude/skills/vmux/SKILL.md
vmux_cli-0.6.0.dist-info/METADATA
vmux_cli-0.6.0.dist-info/WHEEL
vmux_cli-0.6.0.dist-info/entry_points.txt
vmux_cli-0.6.0.dist-info/RECORD
